.hgignore
CHANGELOG.rst
LICENSE
Makefile
README
setup.py
tox.ini
mux/__init__.py
mux/__main__.py
mux/cmdline.py
mux/credentials.py
mux/daemon.py
mux/reciver.py
mux/utils.py
mux_twitter.egg-info/PKG-INFO
mux_twitter.egg-info/SOURCES.txt
mux_twitter.egg-info/dependency_links.txt
mux_twitter.egg-info/entry_points.txt
mux_twitter.egg-info/requires.txt
mux_twitter.egg-info/top_level.txt
mux_twitter.egg-info/zip-safe