Metadata-Version: 1.1
Name: mux-twitter
Version: 0.1
Summary: CLI twitter client using the streaming API
Home-page: http://blitz.works/mux/
Author: Da_Blitz
Author-email: code@pocketnix.org
License: MIT BSD
Download-URL: http://blitz.works/mux/archive/tip.zip
Keywords: twitter streaming asyncio client
Platform: UNKNOWN
Classifier: License :: OSI Approved :: BSD License
Classifier: Operating System :: POSIX :: Linux
Classifier: Programming Language :: Python :: 3
Classifier: Topic :: Communications
Classifier: Topic :: Internet
